Metadata-Version: 1.1
Name: pypia
Version: 0.3.6
Summary: Configuration and connection tools for PIA VPN routes on Linux
Home-page: https://github.com/dagrha/pypia
Author: Dan Hallau
Author-email: pia@hallau.us
License: UNKNOWN
Platform: UNKNOWN
Classifier: Programming Language :: Python :: 3 :: Only
Classifier: License :: OSI Approved :: GNU General Public License v3 (GPLv3)
Classifier: Operating System :: POSIX :: Linux
Classifier: Development Status :: 4 - Beta
Classifier: Environment :: Console
Classifier: Intended Audience :: End Users/Desktop
Classifier: Topic :: Internet
Classifier: Topic :: Internet :: Proxy Servers
